fitsbolt/__init__.py
fitsbolt/channel_mixing.py
fitsbolt/image_loader.py
fitsbolt/read.py
fitsbolt/resize.py
fitsbolt/cfg/__init__.py
fitsbolt/cfg/create_config.py
fitsbolt/cfg/logger.py
fitsbolt/normalisation/NormalisationMethod.py
fitsbolt/normalisation/__init__.py
fitsbolt/normalisation/normalisation.py
fitsbolt-0.1.5.dist-info/licenses/LICENSE
fitsbolt-0.1.5.dist-info/licenses/LICENSES/GPL-3.0
fitsbolt-0.1.5.dist-info/licenses/LICENSES/MIT
fitsbolt-0.1.5.dist-info/METADATA
fitsbolt-0.1.5.dist-info/WHEEL
fitsbolt-0.1.5.dist-info/entry_points.txt
fitsbolt-0.1.5.dist-info/top_level.txt
fitsbolt-0.1.5.dist-info/RECORD
