Metadata-Version: 2.4
Name: fitsbolt
Version: 0.1.5
Summary: Python module to load and process astronomical images
Author: Laslo E. Ruhberg
License-Expression: MIT OR GPL-3.0
Project-URL: Homepage, https://github.com/Lasloruhberg/fitsbolt
Project-URL: Repository, https://github.com/Lasloruhberg/fitsbolt
Project-URL: Issues, https://github.com/Lasloruhberg/fitsbolt/issues
Classifier: Development Status :: 4 - Beta
Classifier: Intended Audience :: Science/Research
Classifier: Programming Language :: Python :: 3
Classifier: Programming Language :: Python :: 3.10
Classifier: Topic :: Scientific/Engineering
Classifier: Topic :: Scientific/Engineering :: Astronomy
Requires-Python: >=3.10
License-File: LICENSE
License-File: LICENSES/GPL-3.0
License-File: LICENSES/MIT
Requires-Dist: astropy>=6.0
Requires-Dist: numpy>=1.26
Requires-Dist: scikit-image
Requires-Dist: tqdm
Requires-Dist: pillow
Requires-Dist: dotmap
Requires-Dist: scipy
Provides-Extra: dev
Requires-Dist: pytest; extra == "dev"
Requires-Dist: pytest-cov; extra == "dev"
Requires-Dist: black; extra == "dev"
Requires-Dist: flake8; extra == "dev"
Dynamic: license-file
